{
"type": "FeatureCollection",
"crs": { "type": "name", "properties": { "name": "urn:ogc:def:crs:OGC:1.3:CRS84" } },
                                                                                
"features": [
{ "type": "Feature", "properties": { "Name": "1 mile", "Description": "" }, "geometry": { "type": "Point", "coordinates": [ -84.55838861, 38.20627508, 0.0 ] } },
{ "type": "Feature", "properties": { "Name": "2 miles", "Description": "" }, "geometry": { "type": "Point", "coordinates": [ -84.55466521, 38.20268004, 0.0 ] } },
{ "type": "Feature", "properties": { "Name": "3 miles", "Description": "" }, "geometry": { "type": "Point", "coordinates": [ -84.55459921, 38.20811819, 0.0 ] } }
]
}
